{"cameraMode":{"drawMode":0,"name":"Shaded","section":"Shading Mode"},"sceneLighting":true,"audioPlay":false,"sceneViewState":{"m_AlwaysRefresh":false,"showFog":true,"showSkybox":true,"showFlares":true,"showImageEffects":true,"showParticleSystems":true,"showVisualEffectGraphs":true,"m_FxEnabled":true},"in2DMode":false,"pivot":{"x":3.584074020385742,"y":6.857304573059082,"z":24.438167572021486},"rotation":{"x":0.12632426619529725,"y":-0.585446298122406,"z":0.09297683089971543,"w":0.7954105734825134},"size":4.724140167236328,"orthographic":false}